.bumpversion.cfg
.codeclimate.yml
.gitignore
.gitmodules
.travis.yml
COPYING
README.md
README.rst
requirements.in
requirements.txt
setup.py
wercker.yml
docs/.gitignore
docs/Makefile
docs/source/_templates
docs/source/conf.py
docs/source/index.rst
docs/source/_static/image.png
docs/source/img/springer.png
misc/index.html
rgmining_ria.egg-info/PKG-INFO
rgmining_ria.egg-info/SOURCES.txt
rgmining_ria.egg-info/dependency_links.txt
rgmining_ria.egg-info/requires.txt
rgmining_ria.egg-info/top_level.txt
ria/__init__.py
ria/bipartite.py
ria/bipartite_sum.py
ria/credibility.py
ria/one.py
tests/__init__.py
tests/bipartite_sum_test.py
tests/bipartite_test.py
tests/credibility_test.py
tests/one_test.py
tests/test_suite.py